tkinter_nav/__init__.py
tkinter_nav/errors.py
tkinter_nav/page.py
tkinter_nav/page_container.py
tkinter_nav/wrapper.py
tkinter_nav-0.0.5.dist-info/LICENSE
tkinter_nav-0.0.5.dist-info/METADATA
tkinter_nav-0.0.5.dist-info/WHEEL
tkinter_nav-0.0.5.dist-info/top_level.txt
tkinter_nav-0.0.5.dist-info/RECORD
