Metadata-Version: 2.1
Name: tkinter-nav
Version: 0.0.5
Summary: Lightweight navigation wrapper for Tkinter
Home-page: https://github.com/maxzaleski/tkinter-nav
Author: Maximilien Zaleski
Author-email: maximilienzaleski@yahoo.com
License: UNKNOWN
Platform: UNKNOWN
Classifier: Programming Language :: Python :: 3
Classifier: License :: OSI Approved :: Apache Software License
Requires-Python: >=3.6
